CRISPR_TAPE/__init__.py
CRISPR_TAPE/__main__.py
CRISPR_TAPE/general_function.py
CRISPR_TAPE/shared_functions.py
CRISPR_TAPE/specific_function.py
CRISPR_TAPE/specific_function_old.py
CRISPR_TAPE-1.0.6.dist-info/LICENSE
CRISPR_TAPE-1.0.6.dist-info/METADATA
CRISPR_TAPE-1.0.6.dist-info/WHEEL
CRISPR_TAPE-1.0.6.dist-info/top_level.txt
CRISPR_TAPE-1.0.6.dist-info/RECORD
