Metadata-Version: 2.1
Name: CRISPR-TAPE
Version: 1.0.6
Summary: A protein-centric CRISPR gRNA design tool for TArgeted Protein Engineering
Home-page: https://github.com/LaboratoryChild/CRISPR-TAPE
Author: Daniel Anderson
Author-email: danielanderson1@hotmail.com
License: Creative Commons Attribution-NonCommercial-NoDerivatives 4.0 International Public License
Classifier: Programming Language :: Python :: 3
Classifier: Operating System :: OS Independent
Requires-Python: >=3.6
License-File: LICENSE
Requires-Dist: numpy ==1.24.4
Requires-Dist: pandas ==2.0.3
Requires-Dist: tqdm ==4.66.1
Requires-Dist: pyinstaller ==6.1.0
Requires-Dist: pytest ==7.4.3
Requires-Dist: build ==1.0.3
